stackapi/__init__.py
stackapi/stackapi.py
StackAPI-0.3.0.dist-info/AUTHORS.rst
StackAPI-0.3.0.dist-info/LICENSE.txt
StackAPI-0.3.0.dist-info/METADATA
StackAPI-0.3.0.dist-info/WHEEL
StackAPI-0.3.0.dist-info/top_level.txt
StackAPI-0.3.0.dist-info/RECORD
