Metadata-Version: 2.1
Name: StackAPI
Version: 0.3.0
Summary: Library for interacting with the Stack Exchange API
Home-page: https://github.com/AWegnerGitHub/StackAPI
Author: Andrew Wegner
Author-email: pypi@andrewwegner.com
Maintainer: Andrew Wegner
Maintainer-email: pypi@andrewwegner.com
License: MIT
Keywords: stackexchange
Classifier: Development Status :: 4 - Beta
Classifier: Intended Audience :: Developers
Classifier: License :: OSI Approved :: MIT License
Classifier: Programming Language :: Python :: 3.9
Classifier: Programming Language :: Python :: 3.10
Classifier: Programming Language :: Python :: 3.11
Classifier: Programming Language :: Python :: 3.12
Classifier: Natural Language :: English
Classifier: Operating System :: OS Independent
Classifier: Topic :: Software Development :: Libraries :: Python Modules
License-File: LICENSE.txt
License-File: AUTHORS.rst
Requires-Dist: requests
Requires-Dist: six
